duptextfinder/__init__.py
duptextfinder/char_fingerprint_builder.py
duptextfinder/duplicate_finder.py
duptextfinder/span.py
duptextfinder/word_fingerprint_builder.py
duptextfinder-0.3.0.dist-info/LICENSE.txt
duptextfinder-0.3.0.dist-info/METADATA
duptextfinder-0.3.0.dist-info/WHEEL
duptextfinder-0.3.0.dist-info/top_level.txt
duptextfinder-0.3.0.dist-info/RECORD
