Metadata-Version: 2.1
Name: duptextfinder
Version: 0.3.0
Summary: Detect duplicated zones in (clinical) text
Home-page: https://github.com/equipe22/duplicatedZoneInClinicalText
License: MIT
Keywords: TEXT,DUPLICATION,DUPLICATE,CLINICAL
License-File: LICENSE.txt
Provides-Extra: tests
Requires-Dist: pytest; extra == "tests"
Requires-Dist: pytest-mock; extra == "tests"
Provides-Extra: ncls
Requires-Dist: ncls>=0.0.66; extra == "ncls"
Requires-Dist: numpy; extra == "ncls"
Provides-Extra: intervaltree
Requires-Dist: intervaltree>=3.0.0; extra == "intervaltree"
